HISTORY.md
LICENSE
MANIFEST.in
README.md
setup.py
zadarest/__init__.py
zadarest/zadarest.py
zadarest.egg-info/PKG-INFO
zadarest.egg-info/SOURCES.txt
zadarest.egg-info/dependency_links.txt
zadarest.egg-info/not-zip-safe
zadarest.egg-info/requires.txt
zadarest.egg-info/top_level.txt
zadarest/endpoints/__init__.py
zadarest/endpoints/base.py
zadarest/endpoints/server.py
zadarest/endpoints/snapshot_policy.py
zadarest/endpoints/volume.py
zadarest/endpoints/vpsa.py