Metadata-Version: 1.1
Name: zadarest
Version: 0.2.1
Summary: python client library for accessing Zadara API
Home-page: https://github.com/nmaekawa/zadarest
Author: naomi maekawa
Author-email: nmaekawa@g.harvard.edu
License: Apache 2.0
Keywords: zadarest
Platform: UNKNOWN
Classifier: Development Status :: 2 - Pre-Alpha
Classifier: Intended Audience :: Developers
Classifier: License :: OSI Approved :: Apache Software License
Classifier: Natural Language :: English
Classifier: Programming Language :: Python :: 2.6
Classifier: Programming Language :: Python :: 2.7
